lemmes
