Metadata-Version: 1.1
Name: lemmes
Version: 1.1.8
Summary: Lemmatizer for spanish language
Home-page: https://github.com/Edux87/lemmes
Author: Edgar Castañeda
Author-email: edaniel15@gmail.com
License: UNKNOWN
Platform: linux
Classifier: Development Status :: 5 - Production/Stable
Classifier: Intended Audience :: Developers
Classifier: Programming Language :: Python
Classifier: Programming Language :: Python :: 2.6
Classifier: Programming Language :: Python :: 2.7
Classifier: Environment :: Console
Classifier: Operating System :: OS Independent
Classifier: License :: OSI Approved :: Apache Software License
Classifier: Topic :: Text Editors :: Text Processing
Classifier: Topic :: Text Editors :: Word Processors
